odoo10_addon_stock_valued_picking_report-10.0.1.0.1-py2.7-nspkg.pth
odoo/addons/stock_valued_picking_report/README.rst
odoo/addons/stock_valued_picking_report/__init__.py
odoo/addons/stock_valued_picking_report/__manifest__.py
odoo/addons/stock_valued_picking_report/i18n/es.po
odoo/addons/stock_valued_picking_report/models/__init__.py
odoo/addons/stock_valued_picking_report/models/res_partner.py
odoo/addons/stock_valued_picking_report/models/stock_pack_operation.py
odoo/addons/stock_valued_picking_report/models/stock_picking.py
odoo/addons/stock_valued_picking_report/report/stock_picking_valued_report.xml
odoo/addons/stock_valued_picking_report/tests/__init__.py
odoo/addons/stock_valued_picking_report/tests/test_stock_picking_valued.py
odoo/addons/stock_valued_picking_report/views/res_partner_view.xml
odoo10_addon_stock_valued_picking_report-10.0.1.0.1.dist-info/DESCRIPTION.rst
odoo10_addon_stock_valued_picking_report-10.0.1.0.1.dist-info/METADATA
odoo10_addon_stock_valued_picking_report-10.0.1.0.1.dist-info/RECORD
odoo10_addon_stock_valued_picking_report-10.0.1.0.1.dist-info/WHEEL
odoo10_addon_stock_valued_picking_report-10.0.1.0.1.dist-info/metadata.json
odoo10_addon_stock_valued_picking_report-10.0.1.0.1.dist-info/namespace_packages.txt
odoo10_addon_stock_valued_picking_report-10.0.1.0.1.dist-info/top_level.txt
